{
  "main": {
    "name":"Ahmed Hamodi",
    "description":"I am a Software Engineering student at the University of Waterloo, and I work as a software engineering intern at a variety of companies. My main tech stack revolves around React and Python!",
    "image":"profilepic.png",
    "bio":"I am a young aspiring Software Engineer, with experience in full-stack development, machine learning, scripting, and automation. I am motivated by my passion for learning new technologies and perfecting my craft. I will never shy away from a challenge and I will always approach tasks with a positive attitude and a willingness to collaborate, explain, and take criticism to continue to improve.",
    "contactmessage":"To get in contact with me, reach out on LinkedIn or via email!",
    "email": "ahmed.r.hamodi@gmail.com",
    "github":"https://github.com/ahmedhamodi",
    "linkedin":"https://www.linkedin.com/in/ahmedhamodi/",
    "website": "https://ahmedhamodi.com/",
    "linkedinurl": "https://www.linkedin.com/in/ahmedhamodi/",
    "social":[
      {
        "name":"email",
        "url":"mailto:ahmed.r.hamodi@gmail.com",
        "className":"fa fa-envelope fa-2x mb-3"
      },
      {
        "name":"github",
        "url":"https://github.com/ahmedhamodi",
        "className":"fa fa-github fa-2x mb-3"
      },
      {
        "name":"linkedin",
        "url":"https://www.linkedin.com/in/ahmedhamodi",
        "className":"fa fa-linkedin fa-2x mb-3"
      },
      {
        "name":"devpost",
        "url":"https://devpost.com/ahmedhamodi",
        "className":"fa fa-code fa-2x mb-3"
      }
    ]
  },
  "resume":{
    "skillmessage":"Below is a quick summary of my technology skills, split into subcategories.",
    "education":[
      {
        "school":"University of Waterloo",
        "degree":"Candidate for Bachelor of Software Engineering",
        "graduated":"SEP 2017 - APR 2022",
        "description":"Elected as Academic Class Rep for every term. Cumulative GPA of 84%. Play in intramural sports including soccer, basketball & volleyball."
      },
      {
        "school":"Bluevale Collegiate Institute",
        "degree":"Ontario Scholar",
        "graduated":"SEP 2013 - JUN 2017",
        "description":"98% grade 12 average. Cumulative average of 96%. Leader of Electric Car Club, Fed Prov, and the peer tutoring group."
      }
    ],
    "work":[
      {
        "company":"Wish",
        "title":"Associate Product Manager Intern",
        "title2":"Associate Product Manager Intern (Part Time)",
        "years":"SEP 2021 - DEC 2021",
        "years2":"DEC 2021 - APR 2022",
        "description":"Defining product vision for Wish's shipping label generation service and returns program.",
        "description2":"Defining Merchant-side experience with Tax Compliance in Indonesia, Columbia, and Chile."
      },
      {
        "company":"Facebook",
        "title":"Software Engineering Intern",
        "years":"JAN 2021 - APR 2021",
        "description":"Working on the Stores team, developing with React and PHP (Hack)."
      },
      {
        "company":"Tealbook",
        "title":"Software Engineering Intern",
        "title2":"Technical Sales Support Specialist",
        "years":"MAY 2020 - AUG 2020",
        "years2":"NOV 2020 - DEC 2020",
        "description":"Worked on the application development team, working with React and Node.js.",
        "description2":"Created a security assessment dataset saving hours of human time."
      },
      {
        "company":"JSI Telecom",
        "title":"Software Engineering Intern",
        "years":"SEP 2019 - DEC 2019",
        "description":"Worked on the data loaders team, working with C# and .NET Core."
      },
      {
        "company":"Condos.ca",
        "title":"Full Stack Engineering Intern",
        "years":"JAN 2019 - APR 2019",
        "description":"Worked on the backend development team, working with PHP (Laravel framework)."
      },
      {
        "company":"OpenText",
        "title":"Software Engineering Intern",
        "years":"MAY 2018 - AUG 2018",
        "description":"Worked on the Exstream application development team, working with Python, TensorFlow, and Keras."
      },
      {
        "company":"FLIR Systems",
        "title":"Operations Engineering Intern",
        "years":"JUN 2017 - SEP 2017",
        "description":"Worked on the test automation team, working with Python and Bash."
      }
    ]
  }
}
